{"path": "C:\\Users\\gyans\\Desktop\\New folder\\New folder\\data1\\1053.jpg", "outputs": {"object": [{"name": "close", "pose": "Unspecified", "truncated": "0", "difficult": "0", "bndbox": {"xmin": "356", "ymin": "1423", "xmax": "453", "ymax": "1524"}}, {"name": "check", "pose": "Unspecified", "truncated": "0", "difficult": "0", "bndbox": {"xmin": "619", "ymin": "1429", "xmax": "732", "ymax": "1524"}}, {"name": "menu", "pose": "Unspecified", "truncated": "0", "difficult": "0", "bndbox": {"xmin": "32", "ymin": "96", "xmax": "114", "ymax": "174"}}]}, "time_labeled": 1677265309954, "labeled": true, "size": {"width": "1080", "height": "1920", "depth": "3"}}