{"path": "C:\\Users\\gyans\\Desktop\\New folder\\New folder\\data1\\1199.jpg", "outputs": {"object": [{"name": "settings", "pose": "Unspecified", "truncated": "0", "difficult": "0", "bndbox": {"xmin": "385", "ymin": "849", "xmax": "426", "ymax": "889"}}, {"name": "add", "pose": "Unspecified", "truncated": "0", "difficult": "0", "bndbox": {"xmin": "433", "ymin": "797", "xmax": "468", "ymax": "832"}}, {"name": "delete", "pose": "Unspecified", "truncated": "0", "difficult": "0", "bndbox": {"xmin": "251", "ymin": "791", "xmax": "290", "ymax": "836"}}, {"name": "info", "pose": "Unspecified", "truncated": "0", "difficult": "0", "bndbox": {"xmin": "478", "ymin": "851", "xmax": "511", "ymax": "886"}}]}, "time_labeled": 1677265309954, "labeled": true, "size": {"width": "1080", "height": "1920", "depth": "3"}}