{"path": "C:\\Users\\gyans\\Desktop\\New folder\\New folder\\data1\\1285.jpg", "outputs": {"object": [{"name": "menu", "pose": "Unspecified", "truncated": "0", "difficult": "0", "bndbox": {"xmin": "33", "ymin": "100", "xmax": "99", "ymax": "155"}}, {"name": "search", "pose": "Unspecified", "truncated": "0", "difficult": "0", "bndbox": {"xmin": "983", "ymin": "95", "xmax": "1046", "ymax": "164"}}, {"name": "arrow forward", "pose": "Unspecified", "truncated": "0", "difficult": "0", "bndbox": {"xmin": "520", "ymin": "1700", "xmax": "579", "ymax": "1758"}}, {"name": "close", "pose": "Unspecified", "truncated": "0", "difficult": "0", "bndbox": {"xmin": "1042", "ymin": "1662", "xmax": "1079", "ymax": "1701"}}, {"name": "expand more", "pose": "Unspecified", "truncated": "0", "difficult": "0", "bndbox": {"xmin": "673", "ymin": "103", "xmax": "721", "ymax": "150"}}]}, "time_labeled": 1677265309954, "labeled": true, "size": {"width": "1080", "height": "1920", "depth": "3"}}