{"path": "C:\\Users\\gyans\\Desktop\\New folder\\New folder\\data1\\1442.jpg", "outputs": {"object": [{"name": "arrow backward", "pose": "Unspecified", "truncated": "0", "difficult": "0", "bndbox": {"xmin": "39", "ymin": "101", "xmax": "109", "ymax": "173"}}, {"name": "share", "pose": "Unspecified", "truncated": "0", "difficult": "0", "bndbox": {"xmin": "49", "ymin": "796", "xmax": "130", "ymax": "882"}}, {"name": "more", "pose": "Unspecified", "truncated": "0", "difficult": "0", "bndbox": {"xmin": "160", "ymin": "793", "xmax": "208", "ymax": "884"}}, {"name": "chat", "pose": "Unspecified", "truncated": "0", "difficult": "0", "bndbox": {"xmin": "90", "ymin": "1194", "xmax": "233", "ymax": "1329"}}]}, "time_labeled": 1677265309954, "labeled": true, "size": {"width": "1080", "height": "1920", "depth": "3"}}