{"path": "C:\\Users\\gyans\\Desktop\\New folder\\New folder\\data1\\1896.jpg", "outputs": {"object": [{"name": "arrow backward", "pose": "Unspecified", "truncated": "0", "difficult": "0", "bndbox": {"xmin": "36", "ymin": "97", "xmax": "109", "ymax": "175"}}, {"name": "arrow forward", "pose": "Unspecified", "truncated": "0", "difficult": "0", "bndbox": {"xmin": "1019", "ymin": "1441", "xmax": "1070", "ymax": "1521"}}, {"name": "arrow forward", "pose": "Unspecified", "truncated": "0", "difficult": "0", "bndbox": {"xmin": "1019", "ymin": "1320", "xmax": "1069", "ymax": "1396"}}, {"name": "arrow forward", "pose": "Unspecified", "truncated": "0", "difficult": "0", "bndbox": {"xmin": "1020", "ymin": "1076", "xmax": "1069", "ymax": "1152"}}, {"name": "arrow forward", "pose": "Unspecified", "truncated": "0", "difficult": "0", "bndbox": {"xmin": "1017", "ymin": "1562", "xmax": "1070", "ymax": "1644"}}, {"name": "arrow forward", "pose": "Unspecified", "truncated": "0", "difficult": "0", "bndbox": {"xmin": "1017", "ymin": "584", "xmax": "1070", "ymax": "664"}}, {"name": "arrow forward", "pose": "Unspecified", "truncated": "0", "difficult": "0", "bndbox": {"xmin": "1020", "ymin": "1198", "xmax": "1068", "ymax": "1274"}}, {"name": "arrow forward", "pose": "Unspecified", "truncated": "0", "difficult": "0", "bndbox": {"xmin": "1019", "ymin": "953", "xmax": "1069", "ymax": "1029"}}, {"name": "arrow forward", "pose": "Unspecified", "truncated": "0", "difficult": "0", "bndbox": {"xmin": "1018", "ymin": "831", "xmax": "1069", "ymax": "908"}}]}, "time_labeled": 1677265309954, "labeled": true, "size": {"width": "1080", "height": "1920", "depth": "3"}}