{"path": "C:\\Users\\gyans\\Desktop\\New folder\\New folder\\data1\\199.jpg", "outputs": {"object": [{"name": "menu", "pose": "Unspecified", "truncated": "0", "difficult": "0", "bndbox": {"xmin": "37", "ymin": "88", "xmax": "116", "ymax": "165"}}, {"name": "search", "pose": "Unspecified", "truncated": "0", "difficult": "0", "bndbox": {"xmin": "108", "ymin": "569", "xmax": "191", "ymax": "650"}}]}, "time_labeled": 1677265309954, "labeled": true, "size": {"width": "1080", "height": "1920", "depth": "3"}}