{"path": "C:\\Users\\gyans\\Desktop\\New folder\\New folder\\data1\\426.jpg", "outputs": {"object": [{"name": "arrow backward", "pose": "Unspecified", "truncated": "0", "difficult": "0", "bndbox": {"xmin": "36", "ymin": "98", "xmax": "113", "ymax": "177"}}, {"name": "add", "pose": "Unspecified", "truncated": "0", "difficult": "0", "bndbox": {"xmin": "916", "ymin": "1620", "xmax": "983", "ymax": "1696"}}, {"name": "play", "pose": "Unspecified", "truncated": "0", "difficult": "0", "bndbox": {"xmin": "872", "ymin": "112", "xmax": "912", "ymax": "160"}}, {"name": "arrow forward", "pose": "Unspecified", "truncated": "0", "difficult": "0", "bndbox": {"xmin": "989", "ymin": "108", "xmax": "1042", "ymax": "162"}}]}, "time_labeled": 1677265309954, "labeled": true, "size": {"width": "1080", "height": "1920", "depth": "3"}}