{"path": "C:\\Users\\gyans\\Desktop\\New folder\\New folder\\data1\\633.jpg", "outputs": {"object": [{"name": "arrow forward", "pose": "Unspecified", "truncated": "0", "difficult": "0", "bndbox": {"xmin": "954", "ymin": "1678", "xmax": "1030", "ymax": "1780"}}, {"name": "arrow backward", "pose": "Unspecified", "truncated": "0", "difficult": "0", "bndbox": {"xmin": "0", "ymin": "95", "xmax": "28", "ymax": "154"}}]}, "time_labeled": 1677265309954, "labeled": true, "size": {"width": "1080", "height": "1920", "depth": "3"}}